neurobooth/__init__.py
neurobooth/face_landmarks.py
neurobooth/pose_landmarks.py
neurobooth-0.1.1.dist-info/LICENSE
neurobooth-0.1.1.dist-info/WHEEL
neurobooth-0.1.1.dist-info/METADATA
neurobooth-0.1.1.dist-info/RECORD
